fastapi_openid_connect/__init__.py
fastapi_openid_connect/models.py
fastapi_openid_connect/provider.py
fastapi_openid_connect/types.py
fastapi_openid_connect/validators.py
fastapi_openid_connect-0.1.0a1.dist-info/LICENSE
fastapi_openid_connect-0.1.0a1.dist-info/METADATA
fastapi_openid_connect-0.1.0a1.dist-info/WHEEL
fastapi_openid_connect-0.1.0a1.dist-info/top_level.txt
fastapi_openid_connect-0.1.0a1.dist-info/RECORD
